slurpy_client/__init__.py
slurpy_client/api_client.py
slurpy_client/configuration.py
slurpy_client/exceptions.py
slurpy_client/rest.py
slurpy_client/api/__init__.py
slurpy_client/api/email_api.py
slurpy_client/api/inbox_api.py
slurpy_client/api/jobs_api.py
slurpy_client/models/__init__.py
slurpy_client/models/http_validation_error.py
slurpy_client/models/validation_error.py
slurpy_client-1.0.7.dist-info/METADATA
slurpy_client-1.0.7.dist-info/WHEEL
slurpy_client-1.0.7.dist-info/top_level.txt
slurpy_client-1.0.7.dist-info/RECORD
