Metadata-Version: 2.1
Name: slurpy-client
Version: 1.0.7
Summary: Slurpy
Home-page: https://github.com/ivegotanidea/slurpy_client
Author: OpenAPI Generator community
Author-email: team@openapitools.org
License: UNKNOWN
Keywords: OpenAPI,OpenAPI-Generator,Slurpy
Platform: UNKNOWN
Requires-Dist: urllib3 (>=1.15)
Requires-Dist: six (>=1.10)
Requires-Dist: certifi
Requires-Dist: python-dateutil
